{
  "kind": "collectionType",
  "collectionName": "links",
  "info": {
    "name": "link"
  },
  "options": {
    "increments": true,
    "timestamps": true,
    "draftAndPublish": true
  },
  "attributes": {
    "buttonLabel": {
      "type": "string",
      "required": true,
      "unique": true
    },
    "buttonLink": {
      "type": "text",
      "required": true
    },
    "icon": {
      "type": "string"
    },
    "category": {
      "type": "enumeration",
      "enum": [
        "Public",
        "Social"
      ]
    }
  }
}
